tabletqt/__init__.py
tabletqt/__main__.py
tabletqt/element.py
tabletqt/exceptions.py
tabletqt/geometry_types.py
tabletqt/layer.py
tabletqt/log.conf
tabletqt/presentation.py
tabletqt/scene_view.py
tabletqt/styledb.py
tabletqt/tablet.py
tabletqt/tablet_config.py
tabletqt/configuration/color_usages.yaml
tabletqt/configuration/colors.yaml
tabletqt/configuration/dash_patterns.yaml
tabletqt/configuration/drawing_types.yaml
tabletqt/configuration/images.yaml
tabletqt/configuration/line_styles.yaml
tabletqt/configuration/stickers.yaml
tabletqt/configuration/styles.py
tabletqt/configuration/symbols.yaml
tabletqt/configuration/text_styles.yaml
tabletqt/configuration/typefaces.yaml
tabletqt/demo/__init__.py
tabletqt/demo/demo1.py
tabletqt/demo/demo2_stickers.py
tabletqt/demo/demo3_shapes.py
tabletqt/demo/demo3b_shapes.py
tabletqt/demo/demo4_lines.py
tabletqt/demo/demo5_symbols.py
tabletqt/demo/demo5sm_symbols.py
tabletqt/demo/demo6_bp_rects.py
tabletqt/demo/demo6_bp_text.py
tabletqt/demo/demo7_images.py
tabletqt/demo/demo8_grid_rect.py
tabletqt/demo/demo9_underlay.py
tabletqt/demo/old/etchasketch.py
tabletqt/demo/old/sketchsymbols.py
tabletqt/graphics/__init__.py
tabletqt/graphics/circle_se.py
tabletqt/graphics/crayon_box.py
tabletqt/graphics/diagnostic_marker.py
tabletqt/graphics/image.py
tabletqt/graphics/line_segment.py
tabletqt/graphics/polygon_se.py
tabletqt/graphics/rectangle_se.py
tabletqt/graphics/symbol.py
tabletqt/graphics/text_element.py
mi_tabletqt-1.2.4.dist-info/LICENSE
mi_tabletqt-1.2.4.dist-info/METADATA
mi_tabletqt-1.2.4.dist-info/WHEEL
mi_tabletqt-1.2.4.dist-info/entry_points.txt
mi_tabletqt-1.2.4.dist-info/top_level.txt
mi_tabletqt-1.2.4.dist-info/RECORD
