Metadata-Version: 2.2
Name: mi-tabletqt
Version: 1.2.4
Summary: Tablet simple 2D drawing interface to Qt
Author-email: Leon Starr <leon_starr@modelint.com>
License: MIT License
Project-URL: repository, https://github.com/modelint/tablet-qt
Project-URL: documentation, https://github.com/modelint/tablet-qt/wiki
Keywords: 2D,draw,graphics,canvas,mbse,xuml,xtuml,sysml
Classifier: License :: OSI Approved :: MIT License
Classifier: Programming Language :: Python
Classifier: Programming Language :: Python :: 3
Requires-Python: >=3.12
License-File: LICENSE
Requires-Dist: mi-configurator
Requires-Dist: pypdf
Requires-Dist: PyQt6
Requires-Dist: PyYAML
Requires-Dist: tomli; python_version < "3.12"
Provides-Extra: build
Requires-Dist: build; extra == "build"
Requires-Dist: twine; extra == "build"
Provides-Extra: dev
Requires-Dist: bump2version; extra == "dev"
Requires-Dist: pytest; extra == "dev"
